Galvatron/__init__.py
Galvatron/model.py
Galvatron-0.0.3.dist-info/LICENSE
Galvatron-0.0.3.dist-info/METADATA
Galvatron-0.0.3.dist-info/WHEEL
Galvatron-0.0.3.dist-info/top_level.txt
Galvatron-0.0.3.dist-info/RECORD
