Metadata-Version: 2.1
Name: Galvatron
Version: 0.0.3
Summary: Swarms - Pytorch
Home-page: https://github.com/kyegomez/Galvatron
Author: Kye Gomez
Author-email: kye@apac.ai
License: MIT
Keywords: artificial intelligence,deep learning,optimizers,Prompt Engineering
Classifier: Development Status :: 4 - Beta
Classifier: Intended Audience :: Developers
Classifier: Topic :: Scientific/Engineering :: Artificial Intelligence
Classifier: License :: OSI Approved :: MIT License
Classifier: Programming Language :: Python :: 3.6
License-File: LICENSE
Requires-Dist: transformers
Requires-Dist: torch
